{
  "startAt":0,
  "maxResults":50,
  "total":7,
  "issues":[
    {
      "self":"https://jira-retail.redprairie.com/rest/api/2.0.alpha1/issue/RWFM-3116",
      "key":"RWFM-3116"
    },
    {
      "self":"https://jira-retail.redprairie.com/rest/api/2.0.alpha1/issue/RWFM-2675",
      "key":"RWFM-2675"
    },
    {
      "self":"https://jira-retail.redprairie.com/rest/api/2.0.alpha1/issue/RWFM-2670",
      "key":"RWFM-2670"
    },
    {
      "self":"https://jira-retail.redprairie.com/rest/api/2.0.alpha1/issue/RWFM-2655",
      "key":"RWFM-2655"
    },
    {
      "self":"https://jira-retail.redprairie.com/rest/api/2.0.alpha1/issue/RWFM-2241",
      "key":"RWFM-2241"
    },
    {
      "self":"https://jira-retail.redprairie.com/rest/api/2.0.alpha1/issue/RWFM-2238",
      "key":"RWFM-2238"
    },
    {
      "self":"https://jira-retail.redprairie.com/rest/api/2.0.alpha1/issue/RWFM-2232",
      "key":"RWFM-2232"
    }
  ]
}